db_utils/__init__.py
db_utils/db_utils.py
mar_db_utils-0.2.dist-info/LICENSE
mar_db_utils-0.2.dist-info/METADATA
mar_db_utils-0.2.dist-info/WHEEL
mar_db_utils-0.2.dist-info/top_level.txt
mar_db_utils-0.2.dist-info/RECORD
